setup.py
d2pi/__init__.py
d2pi/auth.py
d2pi/cache.py
d2pi/client.py
d2pi/config.py
d2pi/eventq.py
d2pi/file.py
d2pi/folder.py
d2pi/lock.py
d2pi/utils.py
d2pi/watch.py
d2pi.egg-info/PKG-INFO
d2pi.egg-info/SOURCES.txt
d2pi.egg-info/dependency_links.txt
d2pi.egg-info/not-zip-safe
d2pi.egg-info/requires.txt
d2pi.egg-info/top_level.txt