Metadata-Version: 1.1
Name: d2pi
Version: 0.0.9.2
Summary: Python library for Dropbox to Raspberry PI
Home-page: http://github.com/GuoJing/Drop2PI
Author: GuoJing
Author-email: soundbbg@gmail.com
License: GPLv3
Platform: UNKNOWN
Classifier: Development Status :: 3 - Alpha
Classifier: License :: OSI Approved :: GNU General Public License v3 (GPLv3)
Classifier: Operating System :: OS Independent
Classifier: Programming Language :: Python
Classifier: Programming Language :: Python :: 2.7
Classifier: Topic :: Software Development :: Libraries :: Python Modules
